Metadata-Version: 1.1
Name: mn-udea
Version: 1.3.2
Summary: numerical methods
Home-page: UNKNOWN
Author: ['icemerman', 'JF_paniagua', 'Jaime Valencia']
Author-email: paniagua1995@hotmail.com
License: GNU GPL V3
Keywords: sample setuptools development
Platform: UNKNOWN
Classifier: Development Status :: 4 - Beta
Classifier: Intended Audience :: Developers
Classifier: Topic :: Software Development :: Build Tools
Classifier: License :: OSI Approved :: MIT License
Classifier: Programming Language :: Python :: 3.5
